loaf/__init__.py
loaf-0.2.21.dist-info/METADATA
loaf-0.2.21.dist-info/WHEEL
loaf-0.2.21.dist-info/top_level.txt
loaf-0.2.21.dist-info/RECORD
