Metadata-Version: 2.2
Name: loaf
Version: 0.2.21
Summary: Effortlessly access your SQL servers and procedures, plus some other utilities!
Author: Posho (Rodrigo Gómez Maitret)
Author-email: <rodrigo.g.maitret@gmail.com>
Keywords: python,SQL,MySQL,MariaDB,PostgreSQL,database,db,easy,loaf,bread
Classifier: Development Status :: 1 - Planning
Classifier: Intended Audience :: Developers
Classifier: Programming Language :: Python :: 3
Classifier: Operating System :: Unix
Classifier: Operating System :: MacOS :: MacOS X
Classifier: Operating System :: Microsoft :: Windows
Requires-Dist: pymysql
Requires-Dist: datetime
Requires-Dist: configparser
Requires-Dist: cryptography
Requires-Dist: psycopg2-binary
Dynamic: author
Dynamic: author-email
Dynamic: classifier
Dynamic: description
Dynamic: description-content-type
Dynamic: keywords
Dynamic: requires-dist
Dynamic: summary
